{
  "config": {
    "configFile": "a:\\learn_playwright\\playwright.config.ts",
    "rootDir": "a:/learn_playwright",
    "forbidOnly": false,
    "fullyParallel": false,
    "globalSetup": null,
    "globalTeardown": null,
    "globalTimeout": 0,
    "grep": {},
    "grepInvert": null,
    "maxFailures": 0,
    "metadata": {
      "actualWorkers": 1
    },
    "preserveOutput": "always",
    "reporter": [
      [
        "dot",
        null
      ],
      [
        "json",
        {
          "outputFile": "jsonReport/jsonReport.json"
        }
      ],
      [
        "html",
        {
          "outputFile": "htmlReport/htmlReport.html",
          "open": "never"
        }
      ]
    ],
    "reportSlowTests": {
      "max": 5,
      "threshold": 15000
    },
    "quiet": false,
    "projects": [
      {
        "outputDir": "a:/learn_playwright/test-results",
        "repeatEach": 1,
        "retries": 0,
        "metadata": {},
        "id": "",
        "name": "",
        "testDir": "a:/learn_playwright",
        "testIgnore": [],
        "testMatch": [
          "/tests/login.spec.ts",
          "/tests/recordPart3.spec.ts",
          "/tests/basicInteractions.spec.ts",
          "/tests/alerts.spec.ts",
          "/tests/frames.spec.ts",
          "/tests/windows.spec.ts",
          "/tests/calendar.spec.ts",
          "/tests/test.spec.ts",
          "/tests/uploadDownload.spec.ts",
          "/tests/uploadDemo.spec.ts"
        ],
        "timeout": 30000
      }
    ],
    "shard": null,
    "updateSnapshots": "missing",
    "version": "1.44.0",
    "workers": 4,
    "webServer": null
  },
  "suites": [
    {
      "title": "tests\\uploadDemo.spec.ts",
      "file": "tests/uploadDemo.spec.ts",
      "column": 0,
      "line": 0,
      "specs": [
        {
          "title": "Add file, Start upload, Cancel upload, Delete selected",
          "ok": true,
          "tags": [],
          "tests": [
            {
              "timeout": 30000,
              "annotations": [],
              "expectedStatus": "passed",
              "projectId": "",
              "projectName": "",
              "results": [
                {
                  "workerIndex": 9,
                  "status": "passed",
                  "duration": 28329,
                  "errors": [],
                  "stdout": [],
                  "stderr": [],
                  "retry": 0,
                  "startTime": "2024-05-29T10:39:44.429Z",
                  "attachments": [
                    {
                      "name": "screenshot",
                      "contentType": "image/png",
                      "path": "a:\\learn_playwright\\test-results\\tests-uploadDemo-Add-file--068ef-ncel-upload-Delete-selected\\test-finished-1.png"
                    },
                    {
                      "name": "video",
                      "contentType": "video/webm",
                      "path": "a:\\learn_playwright\\test-results\\tests-uploadDemo-Add-file--068ef-ncel-upload-Delete-selected\\video.webm"
                    }
                  ]
                }
              ],
              "status": "expected"
            }
          ],
          "id": "603056460293134a7796-59922765243228819ef2",
          "file": "tests/uploadDemo.spec.ts",
          "line": 3,
          "column": 5
        }
      ]
    }
  ],
  "errors": [],
  "stats": {
    "startTime": "2024-05-29T10:39:43.388Z",
    "duration": 29863.094999999972,
    "expected": 1,
    "skipped": 0,
    "unexpected": 0,
    "flaky": 0
  }
}